thedropin/__init__.py
thedropin/emoji.py
thedropin/registration.py
thedropin/release.py
thedropin/version.py
thedropin-0.0.4.dist-info/METADATA
thedropin-0.0.4.dist-info/WHEEL
thedropin-0.0.4.dist-info/top_level.txt
thedropin-0.0.4.dist-info/RECORD
