Metadata-Version: 2.1
Name: thedropin
Version: 0.0.4
Summary: a base Pelican Plugin template.
Home-page: https://github.com/nebulousdog/thedropin
Author: Tom Spalding
Author-email: tom@blackforestbotanics.com
License: MIT
Platform: UNKNOWN
Classifier: Framework :: Pelican :: Plugins
Classifier: Programming Language :: Python :: 3
Classifier: License :: OSI Approved :: MIT License
